reg_my_ip_core/__init__.py
reg_my_ip_core/__main__.py
reg_my_ip_core/_cmd/run.py
reg_my_ip_core/_core/reg_my_ip.py
reg_my_ip_core/digest_tools/__init__.py
reg_my_ip_core/digest_tools/digest_tools.py
reg_my_ip_core/totp_tools/__init__.py
reg_my_ip_core/totp_tools/totp_tools.py
reg_my_ip_core/tx_tools/__init__.py
reg_my_ip_core/tx_tools/tx_tools.py
reg_my_ip_core-0.0.21.dist-info/METADATA
reg_my_ip_core-0.0.21.dist-info/WHEEL
reg_my_ip_core-0.0.21.dist-info/licenses/LICENSE
reg_my_ip_core-0.0.21.dist-info/RECORD
